{
  "posts": [
    {
      "id": 1,
      "title": "json-server",
      "author": "typicode"
    }
  ],
  "comments": [
    {
      "id": 1,
      "body": "some comment",
      "postId": 1
    }
  ],
  "profile": {
    "name": "typicode"
  },
  "customer": [
    {
      "id": 1,
      "name": "Thuận",
      "gender": 1,
      "birthday": "1994-08-11",
      "idCard": 436128312,
      "phone": "0944192105",
      "email": "tthuan@gmail.com",
      "address": "Đà nẵng",
      "customerType": {
        "id": 1,
        "name": "Platinum"
      }
    },
    {
      "id": 2,
      "name": "Sang ",
      "gender": "1",
      "birthday": "2000-08-10",
      "idCard": 537162398,
      "phone": "0914221041",
      "email": "nhsang@gmail.com",
      "address": "Quảng Nam",
      "customerType": {
        "id": 2,
        "name": "Diamond"
      }
    },
    {
      "id": 3,
      "name": "Hoàn",
      "gender": 1,
      "birthday": "2022-08-02",
      "idCard": 576312312,
      "phone": "0914741373",
      "email": "tvhoan@gmail.com",
      "address": "Đà nẵng",
      "customerType": {
        "id": 3,
        "name": "Gold"
      }
    },
    {
      "id": 4,
      "name": "Bích Huyền",
      "birthday": "13-03-1999",
      "gender": 0,
      "idCard": 531672312,
      "phone": "0915897123",
      "email": "ntbhuyen@gmail.com",
      "address": "Hội an",
      "customerType": {
        "id": 4,
        "name": "Silver"
      }
    },
    {
      "id": 5,
      "name": "Trần Thanh Trí",
      "gender": 1,
      "birthday": "2022-08-10",
      "idCard": 123647844,
      "phone": "0978123678",
      "email": "tttri@gmail.com",
      "address": "Quảng Trị",
      "customerType": {
        "id": 5,
        "name": "Member"
      }
    },
    {
      "id": 6,
      "name": "Trần Thanh Sang",
      "gender": 1,
      "birthday": "1997-08-10",
      "idCard": 123647844,
      "phone": "0978123678",
      "email": "tttri@gmail.com",
      "address": "Quảng Trị",
      "customerType": {
        "id": 5,
        "name": "Member"
      }
    },
    {
      "name": "thuan",
      "birthday": "2022-08-20",
      "gender": 1,
      "idCard": "999999993",
      "phone": "+84123123123",
      "email": "tthuan@gmail.com",
      "address": "da nang",
      "customerType": {
        "id": 3,
        "name": "Gold"
      },
      "id": 7
    },
    {
      "id": 8,
      "name": "thuan",
      "gender": "1",
      "birthday": "2022-08-26",
      "idCard": "999999993",
      "phone": "+84123123123",
      "email": "tthuan.17it3@vku.udn.vn",
      "address": "da nangdá",
      "customerType": {
        "id": 2,
        "name": "Diamond"
      }
    }
  ],
  "customerType": [
    {
      "id": 1,
      "name": "Platinum"
    },
    {
      "id": 2,
      "name": "Diamond"
    },
    {
      "id": 3,
      "name": "Gold"
    },
    {
      "id": 4,
      "name": "Silver"
    },
    {
      "id": 5,
      "name": "Member"
    }
  ],
  "facility": [
    {
      "id": 1,
      "name": "PHÒNG SUITE HƯỚNG BIỂN",
      "area": 36,
      "cost": 100000,
      "maxPeople": 10,
      "standardRoom": "normal",
      "descriptionOtherConvenience": "Có hồ bơi",
      "poolArea": 500,
      "numberOfFloors": 2,
      "facilityFree": "gà 51kg",
      "facilityType": {
        "id": 1,
        "name": "Villa"
      },
      "rentType": {
        "id": 1,
        "name": "Theo năm"
      },
      "image": "assets/image/facility/facility1.jpeg"
    },
    {
      "id": 2,
      "name": "PHÒNG STUDIO SUITE HƯỚNG BIỂN",
      "area": 85.8,
      "cost": 100000,
      "maxPeople": 10,
      "standardRoom": "normal",
      "descriptionOtherConvenience": "Có hồ bơi",
      "poolArea": 500,
      "numberOfFloors": 2,
      "facilityFree": "gà 51kg",
      "facilityType": {
        "id": 1,
        "name": "Villa"
      },
      "rentType": {
        "id": 1,
        "name": "Theo năm"
      },
      "image": "assets/image/facility/facility2.jpeg"
    },
    {
      "id": 3,
      "name": "PHÒNG DELUXE HƯỚNG BIỂN",
      "area": 67,
      "cost": 100000,
      "maxPeople": 10,
      "standardRoom": "normal",
      "descriptionOtherConvenience": "Có hồ bơi",
      "poolArea": 500,
      "numberOfFloors": 2,
      "facilityFree": "gà 51kg",
      "facilityType": {
        "id": 1,
        "name": "Villa"
      },
      "rentType": {
        "id": 1,
        "name": "Theo năm"
      },
      "image": "assets/image/facility/facility3.jpeg"
    },
    {
      "id": 4,
      "name": "PHÒNG SUPERIOR HƯỚNG HỒ",
      "area": 56.8,
      "cost": 100000,
      "maxPeople": 10,
      "standardRoom": "normal",
      "descriptionOtherConvenience": "Có hồ bơi",
      "poolArea": 500,
      "numberOfFloors": 2,
      "facilityFree": "gà 51kg",
      "facilityType": {
        "id": 1,
        "name": "Villa"
      },
      "rentType": {
        "id": 1,
        "name": "Theo năm"
      },
      "image": "assets/image/facility/facility4.jpeg"
    },
    {
      "id": 5,
      "name": "PHÒNG DELUXE HƯỚNG VƯỜN",
      "area": 56.8,
      "cost": 100000,
      "maxPeople": 10,
      "standardRoom": "normal",
      "descriptionOtherConvenience": "Có hồ bơi",
      "poolArea": 500,
      "numberOfFloors": 2,
      "facilityFree": "gà 51kg",
      "facilityType": {
        "id": 1,
        "name": "Villa"
      },
      "rentType": {
        "id": 1,
        "name": "Theo năm"
      },
      "image": "assets/image/facility/facility5.jpeg"
    },
    {
      "id": 6,
      "name": "PHÒNG PRESIDENTIAL SUITE",
      "area": 56.8,
      "cost": 100000,
      "maxPeople": 10,
      "standardRoom": "normal",
      "descriptionOtherConvenience": "Có hồ bơi",
      "poolArea": 500,
      "numberOfFloors": 2,
      "facilityFree": "gà 51kg",
      "facilityType": {
        "id": 1,
        "name": "Villa"
      },
      "rentType": {
        "id": 1,
        "name": "Theo năm"
      },
      "image": "assets/image/facility/facility6.jpeg"
    },
    {
      "id": 7,
      "name": "BIỆT THỰ HƯỚNG BIỂN CÓ HỒ BƠI",
      "area": 56.8,
      "cost": 100000,
      "maxPeople": 10,
      "standardRoom": "normal",
      "descriptionOtherConvenience": "Có hồ bơi",
      "poolArea": 500,
      "numberOfFloors": 2,
      "facilityFree": "gà 51kg",
      "facilityType": {
        "id": 1,
        "name": "Villa"
      },
      "rentType": {
        "id": 1,
        "name": "Theo năm"
      },
      "image": "assets/image/facility/facility7.jpeg"
    },
    {
      "id": 8,
      "name": "BIỆT THỰ HƯỚNG VƯỜN CÓ HỒ BƠI",
      "area": 56.8,
      "cost": 100000,
      "maxPeople": 10,
      "standardRoom": "normal",
      "descriptionOtherConvenience": "Có hồ bơi",
      "poolArea": 500,
      "numberOfFloors": 2,
      "facilityFree": "gà 51kg",
      "facilityType": {
        "id": 1,
        "name": "Villa"
      },
      "rentType": {
        "id": 1,
        "name": "Theo năm"
      },
      "image": "assets/image/facility/facility8.jpeg"
    },
    {
      "id": 9,
      "name": "PHÒNG SUPERIOR HƯỚNG VƯỜN",
      "area": 56.8,
      "cost": 100000,
      "maxPeople": 10,
      "standardRoom": "normal",
      "descriptionOtherConvenience": "Có hồ bơi",
      "poolArea": 500,
      "numberOfFloors": 2,
      "facilityFree": "gà 51kg",
      "facilityType": {
        "id": 1,
        "name": "Villa"
      },
      "rentType": {
        "id": 1,
        "name": "Theo năm"
      },
      "image": "assets/image/facility/facility9.jpeg"
    },
    {
      "name": "Thuan Tran",
      "area": "123",
      "cost": "312",
      "maxPeople": "12",
      "rentType": {
        "id": 2,
        "name": "Theo tháng"
      },
      "facilityType": "[object Object]",
      "standardRoom": "dá",
      "descriptionOtherConvenience": null,
      "poolArea": "312",
      "numberOfFloors": "312",
      "facilityFree": "312",
      "image": "assets/image/facility/facility1.jpeg",
      "id": 12
    },
    {
      "name": "Thuan",
      "area": "123",
      "cost": "312",
      "maxPeople": "1",
      "rentType": {
        "id": 3,
        "name": "Theo năm"
      },
      "facilityType": "[object Object]",
      "standardRoom": "dá",
      "descriptionOtherConvenience": null,
      "poolArea": "123",
      "numberOfFloors": "2435",
      "facilityFree": "gà 51kg ok",
      "image": "assets/image/facility/facility1.jpeg",
      "id": 13
    }
  ],
  "rentType": [
    {
      "id": 1,
      "name": "Theo năm"
    },
    {
      "id": 2,
      "name": "Theo tháng"
    },
    {
      "id": 3,
      "name": "Theo năm"
    }
  ],
  "facilityType": [
    {
      "id": 1,
      "name": "Villa"
    },
    {
      "id": 2,
      "name": "Home"
    },
    {
      "id": 3,
      "name": "Room"
    }
  ]
}